LICENSE
weatherstackapi/__init__.py
weatherstackapi/api.py
weatherstackapi/asyncApi.py
weatherstackapi/BaseApi.py
weatherstackapi/types/__init__.py
weatherstackapi/types/astro.py
weatherstackapi/types/current.py
weatherstackapi/types/enums.py
weatherstackapi/types/error.py
weatherstackapi/types/historical.py
weatherstackapi/types/hourly.py
weatherstackapi/types/location.py
weatherstackapi/types/request.py
weatherstackapi/types/response.py
weatherstackapi/types/results.py
weatherstackapi/utility.py
weatherstackapi-1.0.1.dist-info/LICENSE
weatherstackapi-1.0.1.dist-info/METADATA
weatherstackapi-1.0.1.dist-info/WHEEL
weatherstackapi-1.0.1.dist-info/RECORD
